.coveragerc
.gitattributes
.gitignore
.travis.yml
CHANGES.rst
MANIFEST.in
README.rst
base.cfg
bootstrap-4.3.x.sh
bootstrap-5.0.x.sh
plone-4.1.x.cfg
plone-4.2.x.cfg
plone-4.3.x-LP.cfg
plone-4.3.x.cfg
plone-5.0.x.cfg
setup.py
travis.cfg
versions.cfg
Products/__init__.py
Products.Collage.egg-info/PKG-INFO
Products.Collage.egg-info/SOURCES.txt
Products.Collage.egg-info/dependency_links.txt
Products.Collage.egg-info/entry_points.txt
Products.Collage.egg-info/namespace_packages.txt
Products.Collage.egg-info/not-zip-safe
Products.Collage.egg-info/requires.txt
Products.Collage.egg-info/top_level.txt
Products/Collage/__init__.py
Products/Collage/config.py
Products/Collage/configure.zcml
Products/Collage/events.py
Products/Collage/interfaces.py
Products/Collage/profiles.zcml
Products/Collage/testing.py
Products/Collage/upgrades.py
Products/Collage/utilities.py
Products/Collage/viewmanager.py
Products/Collage/browser/__init__.py
Products/Collage/browser/actions.py
Products/Collage/browser/actions.zcml
Products/Collage/browser/collage.py
Products/Collage/browser/configure.zcml
Products/Collage/browser/controlpanel.py
Products/Collage/browser/existingitems.py
Products/Collage/browser/helper.py
Products/Collage/browser/kss.py
Products/Collage/browser/manager.py
Products/Collage/browser/renderer.py
Products/Collage/browser/skins.py
Products/Collage/browser/skins.zcml
Products/Collage/browser/utils.py
Products/Collage/browser/viewlet.py
Products/Collage/browser/viewlets.zcml
Products/Collage/browser/views.py
Products/Collage/browser/views.zcml
Products/Collage/browser/views_dx.zcml
Products/Collage/browser/resources/collage.js
Products/Collage/browser/resources/collage_icon.png
Products/Collage/browser/resources/collage_row_header.jpg
Products/Collage/browser/resources/collagealias_icon.gif
Products/Collage/browser/resources/collagecolumn_icon.png
Products/Collage/browser/resources/collagerow_icon.png
Products/Collage/browser/resources/edit_icon.gif
Products/Collage/browser/resources/icon-copy.gif
Products/Collage/browser/resources/icon-delete.gif
Products/Collage/browser/resources/icon-insert.gif
Products/Collage/browser/resources/icon-object-action.gif
Products/Collage/browser/resources/icon-paste.gif
Products/Collage/browser/resources/icon-plusminus.gif
