Metadata-Version: 1.1
Name: Products.Collage
Version: 1.4.0
Summary: A product to create page compositions in Plone.
Home-page: http://www.plone.org/products/collage
Author: Malthe Borch
Author-email: mborch@gmail.com
License: GPL
Keywords: plone layout composition
Platform: UNKNOWN
Classifier: Programming Language :: Python
Classifier: Framework :: Plone
Classifier: Framework :: Plone :: 4.1
Classifier: Framework :: Plone :: 4.2
Classifier: Framework :: Plone :: 4.3
Classifier: Programming Language :: Python :: 2.7
Classifier: License :: OSI Approved :: GNU General Public License (GPL)
Classifier: Development Status :: 5 - Production/Stable
